{"Credits per Hectare per Year": 20, "Nominal Interest Rate": 0.0235, "Inflation Rate": 0.021, "Registry Account Opening Fee": 0, "Registry Listing Cost per Credit": 0.05, "Registry Conversion Cost Fee per Inspection": 100, "Registry Conversion Cost per Credit above Minimum Threshold of Credits": 0.05, "Registry Levy Cost per Credit": 0.05, "Validation and Verification Application Cost per Inspection": 600, "Validation and Verification Statement Cost per Inspection": 800, "Validation and Verification Inspector Travel Costs per Inspection": 500, "Inspection Cycle Length": 5, "Minimum Threshold of Credits": 2000, "Interest Rate": 0.05, "Payments per Year": 12}