{
     "Site Characteristics": {
          "Site Name": "Dutch Example",
          "Coordinates": [
               0,
               0
          ],
          "Total Area": 1,
          "Peat Type": "Sphagnum",
          "Peat Thickness": 100,
          "Year Rewetting Started": 2022,
          "Baseline Soil Moisture Class": "5+ (Wet (upper eulittoral))",
          "Rewetting Soil Moisture Class": "2+ (Moderate moist)",
          "Baseline Vegetation Class": "G5s:Wet Grassland with Shunt Species",
          "Rewetting Vegetation Class": "G2:Moist Grassland"
     },
     "Baseline Outcomes": {
          "CH4": 2.93,
          "CO2": -3.89,
          "C-Emission GWP Subtotal": -0.96,
          "N2O Direct": 2.4115,
          "N2O Indirect": 819.5314285714285,
          "N2O-Emission GWP Subtotal": 821.9429285714285,
          "Activity GWP Subtotal": 0.0,
          "GWP Total": 820.9829285714285
     },
     "Rewetting Outcomes": {
          "CH4": 0.01,
          "CO2": 19.37,
          "C-Emission GWP Subtotal": 19.380000000000003,
          "N2O Direct": 3.2651785714285717,
          "N2O Indirect": 1033.7839285714285,
          "N2O-Emission GWP Subtotal": 1037.049107142857,
          "Activity GWP Subtotal": 0.039310000000000005,
          "Product GWP Subtotal": -41.79999999999999,
          "GWP Total": 1014.6684171428569
     },
     "Carbon Savings": {
          "GHG Savings Total per Year per Site": -193.68548857142844,
          "GHG Savings Total per Year per Hectare": -193.68548857142844,
          "GHG Savings Stock per Year per Site": -20.34,
          "GHG Savings Stock per Year per Hectare": -20.34,
          "GHG Savings Product Use per Year per Site": -0.039310000000000005,
          "GHG Savings Product Use per Year per Hectare": -0.039310000000000005,
          "Carbon Stock Peat Soil at Start Year (tCO2-eq/site)": 1281.8666666666668,
          "Carbon Stock Peat Soil at Start Year (ton C/site)": 349.6,
          "Carbon Stock Peat Soil at Start Year (tCO2-eq/ha)": 1281.8666666666668,
          "Carbon Stock Peat Soil at Start Year (ton C/ha)": 349.6,
          "Time until Peat is Lost (Baseline Scenario)": -359.2977735422447,
          "Time until Peat is Lost (Rewetting Scenario)": 66.17418043718051
     }
}
